flashqda/__init__.py
flashqda/analyze.py
flashqda/causal_chain.py
flashqda/embedding_utils.py
flashqda/general.py
flashqda/preprocess.py
flashqda/screen.py
flashqda/prompts/__init__.py
flashqda/prompts/label_text.txt
flashqda/prompts/relationships_classify.txt
flashqda/prompts/relationships_extract.txt
flashqda/prompts/tenses.txt
flashqda-1.8.dist-info/LICENSE
flashqda-1.8.dist-info/METADATA
flashqda-1.8.dist-info/WHEEL
flashqda-1.8.dist-info/top_level.txt
flashqda-1.8.dist-info/RECORD
